[
    {
        "name": "20260314",
        "images": [
            "1.png",
            "10.png",
            "2.png",
            "3.png",
            "4.png",
            "5.png",
            "6.png",
            "7.png",
            "8.png",
            "9.png",
            "ComfyUI_02165_.png",
            "ComfyUI_02175_.png",
            "ComfyUI_02177_.png",
            "ComfyUI_02183_.png",
            "ComfyUI_02189_.png",
            "ComfyUI_02193_.png",
            "ComfyUI_02199_.png",
            "ComfyUI_02204_.png",
            "ComfyUI_02207_.png",
            "ComfyUI_02212_.png"
        ]
    },
    {
        "name": "20260313",
        "images": [
            "1.png",
            "10.png",
            "2.png",
            "3.png",
            "4.png",
            "5.png",
            "6.png",
            "7.png",
            "8.png",
            "9.png",
            "ComfyUI_02125_.png",
            "ComfyUI_02126_.png",
            "ComfyUI_02130_.png",
            "ComfyUI_02133_.png",
            "ComfyUI_02138_.png",
            "ComfyUI_02141_.png",
            "ComfyUI_02148_.png",
            "ComfyUI_02150_.png",
            "ComfyUI_02152_.png",
            "ComfyUI_02163_.png"
        ]
    },
    {
        "name": "20260312",
        "images": [
            "1.png",
            "10.png",
            "2.png",
            "3.png",
            "4.png",
            "5.png",
            "6.png",
            "7.png",
            "8.png",
            "9.png",
            "ComfyUI_02042_.png",
            "ComfyUI_02044_.png",
            "ComfyUI_02048_.png",
            "ComfyUI_02053_.png",
            "ComfyUI_02058_.png",
            "ComfyUI_02060_.png",
            "ComfyUI_02061_.png",
            "ComfyUI_02062_.png",
            "ComfyUI_02066_.png",
            "ComfyUI_02067_.png",
            "ComfyUI_02068_.png",
            "ComfyUI_02072_.png",
            "ComfyUI_02077_.png",
            "ComfyUI_02082_.png",
            "ComfyUI_02083_.png",
            "ComfyUI_02088_.png",
            "ComfyUI_02089_.png",
            "ComfyUI_02091_.png",
            "ComfyUI_02097_.png",
            "ComfyUI_02116_.png"
        ]
    },
    {
        "name": "20260311",
        "images": [
            "1.png",
            "10.png",
            "2.png",
            "3.png",
            "4.png",
            "5.png",
            "6.png",
            "7.png",
            "8.png",
            "9.png",
            "ComfyUI_01986_.png",
            "ComfyUI_01990_.png",
            "ComfyUI_01992_.png",
            "ComfyUI_01996_.png",
            "ComfyUI_01998_.png",
            "ComfyUI_02002_.png",
            "ComfyUI_02005_.png",
            "ComfyUI_02008_.png",
            "ComfyUI_02018_.png",
            "ComfyUI_02020_.png",
            "ComfyUI_02030_.png"
        ]
    },
    {
        "name": "20260310",
        "images": [
            "1.png",
            "10.png",
            "2.png",
            "3.png",
            "4.png",
            "5.png",
            "6.png",
            "7.png",
            "8.png",
            "9.png",
            "ComfyUI_01928_.png",
            "ComfyUI_01929_.png",
            "ComfyUI_01932_.png",
            "ComfyUI_01934_.png",
            "ComfyUI_01935_.png",
            "ComfyUI_01944_.png",
            "ComfyUI_01952_.png",
            "ComfyUI_01954_.png",
            "ComfyUI_01956_.png",
            "ComfyUI_01963_.png",
            "ComfyUI_01971_.png",
            "ComfyUI_01978_.png",
            "pixi.png"
        ]
    },
    {
        "name": "20260309",
        "images": [
            "1.png",
            "10.png",
            "2.png",
            "3.png",
            "4.png",
            "5.png",
            "6.png",
            "7.png",
            "8.png",
            "9.png",
            "ComfyUI_01877_.png",
            "ComfyUI_01880_.png",
            "ComfyUI_01882_.png",
            "ComfyUI_01883_.png",
            "ComfyUI_01886_.png",
            "ComfyUI_01890_.png",
            "ComfyUI_01892_.png",
            "ComfyUI_01893_.png",
            "ComfyUI_01896_.png",
            "ComfyUI_01903_.png",
            "ComfyUI_01904_.png",
            "ComfyUI_01906_.png",
            "ComfyUI_01911_.png",
            "ComfyUI_01913_.png",
            "ComfyUI_01919_.png"
        ]
    },
    {
        "name": "20260308",
        "images": [
            "1.png",
            "10.png",
            "2.png",
            "3.png",
            "4.png",
            "5.png",
            "6.png",
            "7.png",
            "8.png",
            "9.png",
            "ComfyUI_01819_.png",
            "ComfyUI_01829_.png",
            "ComfyUI_01840_.png",
            "ComfyUI_01845_.png",
            "ComfyUI_01852_.png",
            "ComfyUI_01862_.png",
            "ComfyUI_01871_.png",
            "ComfyUI_01876_.png"
        ]
    },
    {
        "name": "20260307",
        "images": [
            "1.png",
            "10.png",
            "2.png",
            "3.png",
            "4.png",
            "5.png",
            "6.png",
            "7.png",
            "8.png",
            "9.png",
            "ComfyUI_01767_.png",
            "ComfyUI_01772_.png",
            "ComfyUI_01779_.png",
            "ComfyUI_01784_.png",
            "ComfyUI_01789_.png",
            "ComfyUI_01791_.png",
            "ComfyUI_01794_.png",
            "ComfyUI_01795_.png",
            "ComfyUI_01800_.png",
            "ComfyUI_01804_.png"
        ]
    },
    {
        "name": "20260306",
        "images": [
            "1.png",
            "10.png",
            "2.png",
            "3.png",
            "4.png",
            "5.png",
            "6.png",
            "7.png",
            "8.png",
            "9.png",
            "ComfyUI_01718_.png",
            "ComfyUI_01719_.png",
            "ComfyUI_01720_.png",
            "ComfyUI_01723_.png",
            "ComfyUI_01724_.png",
            "ComfyUI_01727_.png",
            "ComfyUI_01737_.png",
            "ComfyUI_01740_.png",
            "ComfyUI_01742_.png",
            "ComfyUI_01745_.png",
            "ComfyUI_01750_.png",
            "ComfyUI_01755_.png",
            "eee.png",
            "www.png"
        ]
    },
    {
        "name": "20260305",
        "images": [
            "1.png",
            "10.png",
            "2.png",
            "3.png",
            "4.png",
            "5.png",
            "6.png",
            "7.png",
            "8.png",
            "9.png",
            "ComfyUI_01660_.png",
            "ComfyUI_01664_.png",
            "ComfyUI_01669_.png",
            "ComfyUI_01675_.png",
            "ComfyUI_01680_.png",
            "ComfyUI_01687_.png",
            "ComfyUI_01712_.png",
            "pixiv.png",
            "uuu.png",
            "xxx.png"
        ]
    },
    {
        "name": "20260304",
        "images": [
            "1.png",
            "10.png",
            "2.png",
            "3.png",
            "4.png",
            "5.png",
            "6.png",
            "7.png",
            "8.png",
            "9.png",
            "ComfyUI_01595_.png",
            "ComfyUI_01602_.png",
            "ComfyUI_01604_.png",
            "ComfyUI_01613_.png",
            "ComfyUI_01618_.png",
            "ComfyUI_01624_.png",
            "ComfyUI_01632_.png",
            "ComfyUI_01658_.png"
        ]
    },
    {
        "name": "20260303",
        "images": [
            "1.png",
            "10.png",
            "2.png",
            "3.png",
            "4.png",
            "5.png",
            "6.png",
            "7.png",
            "8.png",
            "9.png",
            "ComfyUI_01523_.png",
            "ComfyUI_01524_.png",
            "ComfyUI_01528_.png",
            "ComfyUI_01536_.png",
            "ComfyUI_01560_.png",
            "ComfyUI_01565_.png",
            "ComfyUI_01567_.png",
            "ComfyUI_01568_.png",
            "ComfyUI_01569_.png",
            "ComfyUI_01584_.png",
            "aw.png",
            "eee.png",
            "fff.png",
            "pixiv.png",
            "tttt.png"
        ]
    },
    {
        "name": "20260302",
        "images": [
            "1.png",
            "10.png",
            "2.png",
            "3.png",
            "4.png",
            "5.png",
            "6.png",
            "7.png",
            "8.png",
            "9.png",
            "ComfyUI_01467_.png",
            "ComfyUI_01468_.png",
            "ComfyUI_01470_.png",
            "ComfyUI_01472_.png",
            "ComfyUI_01474_.png",
            "ComfyUI_01475_.png",
            "ComfyUI_01481_.png",
            "ComfyUI_01487_.png",
            "ComfyUI_01514_.png",
            "ComfyUI_01519_.png"
        ]
    },
    {
        "name": "20260301",
        "images": [
            "1.png",
            "10.png",
            "2.png",
            "3.png",
            "4.png",
            "5.png",
            "6.png",
            "7.png",
            "8.png",
            "9.png",
            "ComfyUI_01428_.png",
            "ComfyUI_01429_.png",
            "ComfyUI_01432_.png",
            "ComfyUI_01435_.png",
            "ComfyUI_01439_.png",
            "ComfyUI_01443_.png",
            "ComfyUI_01449_.png",
            "ComfyUI_01459_.png"
        ]
    },
    {
        "name": "20260228",
        "images": [
            "1.png",
            "10.png",
            "2.png",
            "3.png",
            "4.png",
            "5.png",
            "6.png",
            "7.png",
            "8.png",
            "9.png",
            "ComfyUI_01385_.png",
            "ComfyUI_01387_.png",
            "ComfyUI_01390_.png",
            "ComfyUI_01394_.png",
            "ComfyUI_01395_.png",
            "ComfyUI_01396_.png",
            "ComfyUI_01405_.png",
            "ComfyUI_01411_.png",
            "ComfyUI_01425_.png"
        ]
    },
    {
        "name": "20260227",
        "images": [
            "1.png",
            "10.png",
            "2.png",
            "3.png",
            "4.png",
            "5.png",
            "6.png",
            "7.png",
            "8.png",
            "9.png",
            "ComfyUI_01340_.png",
            "ComfyUI_01341_.png",
            "ComfyUI_01343_.png",
            "ComfyUI_01345_.png",
            "ComfyUI_01350_.png",
            "ComfyUI_01351_.png",
            "ComfyUI_01352_.png",
            "ComfyUI_01353_.png",
            "ComfyUI_01355_.png",
            "ComfyUI_01362_.png",
            "ComfyUI_01363_.png",
            "ComfyUI_01370_.png",
            "ComfyUI_01371_.png"
        ]
    },
    {
        "name": "20260226",
        "images": [
            "1.png",
            "10.png",
            "2.png",
            "3.png",
            "4.png",
            "5.png",
            "6.png",
            "7.png",
            "8.png",
            "9.png",
            "ComfyUI_01306_.png",
            "ComfyUI_01307_.png",
            "ComfyUI_01310_.png",
            "ComfyUI_01315_.png",
            "ComfyUI_01317_.png",
            "ComfyUI_01321_.png",
            "ComfyUI_01323_.png",
            "ComfyUI_01326_.png",
            "ComfyUI_01329_.png",
            "ComfyUI_01335_.png"
        ]
    },
    {
        "name": "20260225",
        "images": [
            "1.png",
            "10.png",
            "2.png",
            "3.png",
            "4.png",
            "5.png",
            "6.png",
            "7.png",
            "8.png",
            "9.png",
            "ComfyUI_01258_.png",
            "ComfyUI_01263_.png",
            "ComfyUI_01264_.png",
            "ComfyUI_01265_.png"
        ]
    },
    {
        "name": "20260224",
        "images": [
            "1.png",
            "10.png",
            "2.png",
            "3.png",
            "4.png",
            "5.png",
            "6.png",
            "7.png",
            "8.png",
            "9.png",
            "ComfyUI_01195_.png",
            "ComfyUI_01196_.png",
            "ComfyUI_01204_.png",
            "ComfyUI_01214_.png",
            "ComfyUI_01218_.png",
            "ComfyUI_01226_.png",
            "ComfyUI_01239_.png",
            "ComfyUI_01241_.png",
            "pixiv.png",
            "pixiv2.png"
        ]
    },
    {
        "name": "20260223",
        "images": [
            "1.png",
            "10.png",
            "2.png",
            "3.png",
            "4.png",
            "5.png",
            "6.png",
            "7.png",
            "8.png",
            "9.png",
            "ComfyUI_01149_.png",
            "ComfyUI_01151_.png",
            "ComfyUI_01154_.png",
            "ComfyUI_01158_.png",
            "ComfyUI_01161_.png",
            "ComfyUI_01164_.png",
            "ComfyUI_01165_.png",
            "ComfyUI_01166_.png",
            "ComfyUI_01169_.png",
            "ComfyUI_01170_.png",
            "ComfyUI_01184_.png"
        ]
    },
    {
        "name": "20260222",
        "images": [
            "1.png",
            "10.png",
            "2.png",
            "3.png",
            "4.png",
            "5.png",
            "6.png",
            "7.png",
            "8.png",
            "9.png",
            "ComfyUI_01042_.png",
            "ComfyUI_01052_.png",
            "ComfyUI_01053_.png",
            "ComfyUI_01055_.png",
            "ComfyUI_01056_.png",
            "ComfyUI_01057_.png",
            "ComfyUI_01058_.png",
            "ComfyUI_01059_.png",
            "ComfyUI_01060_.png",
            "ComfyUI_01062_.png",
            "ComfyUI_01065_.png",
            "ComfyUI_01067_.png",
            "ComfyUI_01069_.png",
            "ComfyUI_01073_.png",
            "ComfyUI_01078_.png",
            "ComfyUI_01081_.png",
            "ComfyUI_01084_.png",
            "ComfyUI_01087_.png",
            "ComfyUI_01089_.png",
            "ComfyUI_01099_.png",
            "ComfyUI_01100_.png",
            "ComfyUI_01102_.png",
            "ComfyUI_01113_.png",
            "ComfyUI_01126_.png",
            "ComfyUI_01139_.png",
            "pixiv (2).png",
            "pixiv.png"
        ]
    },
    {
        "name": "20260221",
        "images": [
            "1.png",
            "10.png",
            "2.png",
            "3.png",
            "4.png",
            "5.png",
            "6.png",
            "7.png",
            "8.png",
            "9.png",
            "ComfyUI_01016_.png",
            "ComfyUI_01017_.png",
            "ComfyUI_01020_.png",
            "ComfyUI_01028_.png"
        ]
    },
    {
        "name": "20260220",
        "images": [
            "1.png",
            "10.png",
            "2.png",
            "3.png",
            "4.png",
            "5.png",
            "6.png",
            "7.png",
            "8.png",
            "9.png",
            "ComfyUI_00977_.png",
            "ComfyUI_00980_.png",
            "ComfyUI_00983_.png",
            "ComfyUI_01008_.png",
            "ComfyUI_01010_.png"
        ]
    },
    {
        "name": "20260219",
        "images": [
            "1.png",
            "10.png",
            "2.png",
            "3.png",
            "4.png",
            "5.png",
            "6.png",
            "7.png",
            "8.png",
            "9.png",
            "ComfyUI_00917_.png",
            "ComfyUI_00920_.png",
            "ComfyUI_00922_.png",
            "ComfyUI_00929_.png",
            "ComfyUI_00930_.png",
            "ComfyUI_00932_.png",
            "ComfyUI_00933_.png",
            "ComfyUI_00935_.png",
            "ComfyUI_00940_.png",
            "ComfyUI_00944_.png",
            "ComfyUI_00948_.png",
            "ComfyUI_00954_.png",
            "pixiv.png"
        ]
    },
    {
        "name": "20260218",
        "images": [
            "1.png",
            "10.png",
            "2.png",
            "3.png",
            "4.png",
            "5.png",
            "6.png",
            "7.png",
            "8.png",
            "9.png",
            "ComfyUI_00884_.png",
            "ComfyUI_00891_.png",
            "ComfyUI_00900_.png",
            "ComfyUI_00901_.png",
            "ComfyUI_00903_.png",
            "ComfyUI_00909_.png"
        ]
    },
    {
        "name": "20260217",
        "images": [
            "1.png",
            "10.png",
            "2.png",
            "3.png",
            "4.png",
            "5.png",
            "6.png",
            "7.png",
            "8.png",
            "9.png",
            "ComfyUI_00842_.png",
            "ComfyUI_00845_.png",
            "ComfyUI_00853_.png",
            "ComfyUI_00855_.png",
            "ComfyUI_00857_.png",
            "ComfyUI_00865_.png",
            "ComfyUI_00880_.png"
        ]
    },
    {
        "name": "20260216",
        "images": [
            "1.png",
            "10.png",
            "2.png",
            "3.png",
            "4.png",
            "5.png",
            "6.png",
            "7.png",
            "8.png",
            "9.png",
            "ComfyUI_00800_.png",
            "ComfyUI_00803_.png",
            "ComfyUI_00810_.png",
            "ComfyUI_00820_.png",
            "ComfyUI_00828_.png",
            "ComfyUI_00841_.png"
        ]
    },
    {
        "name": "20260215",
        "images": [
            "1.png",
            "10.png",
            "2.png",
            "3.png",
            "4.png",
            "5.png",
            "6.png",
            "7.png",
            "8.png",
            "9.png",
            "ComfyUI_00771_.png",
            "ComfyUI_00775_.png",
            "ComfyUI_00776_.png",
            "ComfyUI_00780_.png",
            "ComfyUI_00782_.png",
            "ComfyUI_00786_.png"
        ]
    },
    {
        "name": "20260214",
        "images": [
            "1.png",
            "10.png",
            "2.png",
            "3.png",
            "4.png",
            "5.png",
            "6.png",
            "7.png",
            "8.png",
            "9.png",
            "ComfyUI_00712_.png",
            "ComfyUI_00715_.png",
            "ComfyUI_00717_.png",
            "ComfyUI_00720_.png",
            "ComfyUI_00721_.png",
            "ComfyUI_00725_.png",
            "ComfyUI_00726_.png",
            "ComfyUI_00732_.png",
            "ComfyUI_00752_.png",
            "ComfyUI_00753_.png",
            "ComfyUI_00762_.png",
            "ComfyUI_00763_.png",
            "ComfyUI_00766_.png"
        ]
    },
    {
        "name": "20260213",
        "images": [
            "1.png",
            "10.png",
            "2.png",
            "3.png",
            "4.png",
            "5.png",
            "6.png",
            "7.png",
            "8.png",
            "9.png",
            "ComfyUI_00678_.png",
            "ComfyUI_00680_.png",
            "ComfyUI_00682_.png",
            "ComfyUI_00687_.png",
            "ComfyUI_00688_.png",
            "ComfyUI_00690_.png",
            "ComfyUI_00693_.png",
            "ComfyUI_00697_.png",
            "ComfyUI_00700_.png",
            "ComfyUI_00706_.png"
        ]
    },
    {
        "name": "20260212",
        "images": [
            "1.png",
            "10.png",
            "2.png",
            "3.png",
            "4.png",
            "5.png",
            "6.png",
            "7.png",
            "8.png",
            "9.png",
            "ComfyUI_00642_.png",
            "ComfyUI_00646_.png",
            "ComfyUI_00649_.png",
            "ComfyUI_00656_.png",
            "ComfyUI_00658_.png",
            "ComfyUI_00664_.png",
            "ComfyUI_00666_.png",
            "ComfyUI_00670_.png",
            "ComfyUI_00676_.png"
        ]
    },
    {
        "name": "20260211",
        "images": [
            "1.png",
            "10.png",
            "2.png",
            "3.png",
            "4.png",
            "5.png",
            "6.png",
            "7.png",
            "8.png",
            "9.png",
            "ComfyUI_00578_.png",
            "ComfyUI_00580_.png",
            "ComfyUI_00581_.png",
            "ComfyUI_00583_.png",
            "ComfyUI_00584_.png",
            "ComfyUI_00585_.png",
            "ComfyUI_00591_.png",
            "ComfyUI_00595_.png",
            "ComfyUI_00596_.png",
            "ComfyUI_00604_.png",
            "ComfyUI_00608_.png",
            "ComfyUI_00613_.png",
            "ComfyUI_00626_.png",
            "ComfyUI_00629_.png",
            "ComfyUI_00632_.png",
            "ComfyUI_00641_.png",
            "pixiv.png"
        ]
    },
    {
        "name": "20260210",
        "images": [
            "1.png",
            "10.png",
            "2.png",
            "3.png",
            "4.png",
            "5.png",
            "6.png",
            "7.png",
            "8.png",
            "9.png",
            "ComfyUI_00472_.png",
            "ComfyUI_00477_.png",
            "ComfyUI_00479_.png",
            "ComfyUI_00481_.png",
            "ComfyUI_00483_.png",
            "ComfyUI_00484_.png",
            "ComfyUI_00489_.png",
            "ComfyUI_00499_.png",
            "ComfyUI_00509_.png",
            "ComfyUI_00515_.png",
            "ComfyUI_00528_.png",
            "ComfyUI_00529_.png",
            "ComfyUI_00546_.png",
            "ComfyUI_00550_.png",
            "ComfyUI_00564_.png",
            "ComfyUI_00574_.png",
            "dg.png",
            "pixiv.png",
            "pixiv1.png"
        ]
    },
    {
        "name": "20260209",
        "images": [
            "1.png",
            "10.png",
            "2.png",
            "3.png",
            "4.png",
            "5.png",
            "6.png",
            "7.png",
            "8.png",
            "9.png",
            "ComfyUI_00385_.png",
            "ComfyUI_00389_.png",
            "ComfyUI_00398_.png",
            "ComfyUI_00401_.png",
            "ComfyUI_00408_.png",
            "ComfyUI_00415_.png",
            "ComfyUI_00416_.png",
            "ComfyUI_00420_.png",
            "ComfyUI_00424_.png",
            "ComfyUI_00427_.png",
            "ComfyUI_00429_.png",
            "ComfyUI_00432_.png",
            "ComfyUI_00449_.png",
            "ComfyUI_00458_.png",
            "ComfyUI_00459_.png",
            "ComfyUI_00460_.png",
            "ComfyUI_00464_.png",
            "ComfyUI_00469_.png",
            "pixiv.png",
            "pixiv1.png"
        ]
    }
]